netbox_project_quota/__init__.py
netbox_project_quota/filtersets.py
netbox_project_quota/forms.py
netbox_project_quota/navigation.py
netbox_project_quota/tables.py
netbox_project_quota/template_content.py
netbox_project_quota/urls.py
netbox_project_quota/api/__init__.py
netbox_project_quota/api/serializers.py
netbox_project_quota/api/urls.py
netbox_project_quota/api/views.py
netbox_project_quota/migrations/0001_initial.py
netbox_project_quota/migrations/__init__.py
netbox_project_quota/models/__init__.py
netbox_project_quota/models/project.py
netbox_project_quota/models/quotatemplate.py
netbox_project_quota/templates/netbox_project_quota/project.html
netbox_project_quota/templates/netbox_project_quota/quotatemplate.html
netbox_project_quota/templates/netbox_project_quota/generic/bulk_remove.html
netbox_project_quota/templates/netbox_project_quota/inc/project_info.html
netbox_project_quota/templates/project_views/device.html
netbox_project_quota/templates/project_views/device_base.html
netbox_project_quota/templates/project_views/ipaddress.html
netbox_project_quota/templates/project_views/ipaddress_base.html
netbox_project_quota/templates/project_views/project_add_contact.html
netbox_project_quota/templates/project_views/project_add_devices.html
netbox_project_quota/templates/project_views/project_add_ipaddress.html
netbox_project_quota/templates/project_views/project_add_virtualmachine.html
netbox_project_quota/templates/project_views/project_user.html
netbox_project_quota/templates/project_views/project_user_base.html
netbox_project_quota/templates/project_views/project_user_remove.html
netbox_project_quota/templates/project_views/virtualmachine.html
netbox_project_quota/templates/project_views/virtualmachine_base.html
netbox_project_quota/views/__init__.py
netbox_project_quota/views/pjcontact.py
netbox_project_quota/views/pjdevice.py
netbox_project_quota/views/pjipaddress.py
netbox_project_quota/views/pjvirtualmachine.py
netbox_project_quota/views/project.py
netbox_project_quota-1.0.9.dist-info/LICENSE
netbox_project_quota-1.0.9.dist-info/METADATA
netbox_project_quota-1.0.9.dist-info/WHEEL
netbox_project_quota-1.0.9.dist-info/entry_points.txt
netbox_project_quota-1.0.9.dist-info/top_level.txt
netbox_project_quota-1.0.9.dist-info/RECORD
