Metadata-Version: 2.1
Name: netbox-project-quota
Version: 1.0.9
Summary: Netbox Plugin for Manage Project
Home-page: UNKNOWN
License: UNKNOWN
Platform: UNKNOWN
License-File: LICENSE
